Metadata-Version: 2.1
Name: dvadmin-celery-newcode
Version: 0.0.3
Summary: 适用于 django-vue-admin 的celery异步插件
Home-page: https://gitee.com/huge-dream/dvadmin-celery
Author: DVAdmin
Author-email: liqiang@django-vue-admin.com
Classifier: Programming Language :: Python :: 3
Classifier: License :: OSI Approved :: MIT License
Classifier: Operating System :: OS Independent
Requires-Python: >=3.7, <4
License-File: LICENSE
Requires-Dist: django-celery-beat (>=2.2.1)
Requires-Dist: tenant-schemas-celery (>=1.0.1)
Requires-Dist: django-redis (>=5.0.0)
Requires-Dist: django-celery-results (>=2.2.0)
